codecraft/__init__.py
codecraft/agent.py
codecraft/cli.py
codecraft/completer.py
codecraft/conf.py
codecraft/context.py
codecraft/core.py
codecraft/models.py
codecraft/prompts/COVERAGE_INSTRUCTION.txt
codecraft/prompts/DEV_INSTRUCTIONS.txt
codecraft/prompts/OUTPUT_INSTRUCTIONS.txt
codecraft/prompts/SYSTEM_PROMPT.txt
codecraft/prompts/__init__.py
codecraft/repomap.py
codecraft/tests/.coverage
codecraft/tests/.gitignore
codecraft/tests/__init__.py
codecraft/tests/test_agent.py
codecraft/tests/test_cli.py
codecraft/tests/test_completer.py
codecraft/tests/test_core.py
codecraft/tests/test_diff.py
codecraft/tests/test_git.py
codecraft/tests/test_models.py
codecraft/tests/test_mr.py
codecraft/tests/test_prompts.py
codecraft/tests/test_repomap.py
codecraft/tests/test_tools.py
codecraft/tools/__init__.py
codecraft/tools/context.py
codecraft/tools/diff.py
codecraft/tools/git.py
codecraft/tools/mr.py
codecraft/tools/pytest.py
codecraft-0.0.1.dist-info/METADATA
codecraft-0.0.1.dist-info/WHEEL
codecraft-0.0.1.dist-info/entry_points.txt
codecraft-0.0.1.dist-info/RECORD
