Metadata-Version: 2.1
Name: codecraft
Version: 0.0.1
Summary: AI code assistant to help you write code faster, cover it with tests and more
License: MIT
Author: Aleksandr Lifanov
Author-email: lifanov@welltory.app
Requires-Python: >=3.10,<4.0
Classifier: License :: OSI Approved :: MIT License
Classifier: Programming Language :: Python :: 3
Classifier: Programming Language :: Python :: 3.10
Classifier: Programming Language :: Python :: 3.11
Classifier: Programming Language :: Python :: 3.12
Requires-Dist: langchain (>=0.0.350,<0.0.351)
Requires-Dist: openai (>=1.6.1,<2.0.0)
Requires-Dist: prompt_toolkit (>=3.0.43,<4.0.0)
Requires-Dist: pydantic (>=1.10.7,<2.0.0)
Requires-Dist: pytest-cov (>=4.1.0,<5.0.0)
Requires-Dist: pytest-xdist (>=3.5.0,<4.0.0)
Requires-Dist: python-dotenv (>=1.0.0,<2.0.0)
Requires-Dist: structlog (>=23.3.0,<24.0.0)
Requires-Dist: termcolor (>=2.3.0,<3.0.0)
Requires-Dist: tiktoken (>=0.3.3,<0.4.0)
Requires-Dist: tree-sitter-languages (>=1.9.1,<2.0.0)
Requires-Dist: yaspin (>=3.0.1,<4.0.0)
